roc/__init__.py
roc/dingo/__init__.py
roc/dingo/commands.py
roc/dingo/constants.py
roc/dingo/descriptor.json
roc/dingo/exceptions.py
roc/dingo/models/__init__.py
roc/dingo/models/data.py
roc/dingo/models/file.py
roc/dingo/models/packet.py
roc/dingo/models/versions/README.rst
roc/dingo/models/versions/SQL/roc_dingo_0004__downgrade.sql
roc/dingo/models/versions/SQL/roc_dingo_0025_create_view_anomalies_per_day.sql
roc/dingo/models/versions/SQL/roc_dingo_0025_create_view_total_events.sql
roc/dingo/models/versions/SQL/roc_dingo_0025_insert_into_anomalies.sql
roc/dingo/models/versions/SQL/roc_dingo_0026_create_view_anomalies_per_day.sql
roc/dingo/models/versions/SQL/roc_dingo_0026_create_view_rpw_events_per_day.sql
roc/dingo/models/versions/SQL/roc_dingo_0026_insert_into_events.sql
roc/dingo/models/versions/SQL/roc_dingo_0027_modifiy_view_rpw_events_per_day.sql
roc/dingo/models/versions/SQL/roc_dingo_0028__downgrade.sql
roc/dingo/models/versions/SQL/roc_dingo_0028__upgrade.sql
roc/dingo/models/versions/SQL/roc_dingo_0029__downgrade.sql
roc/dingo/models/versions/SQL/roc_dingo_0029__upgrade.sql
roc/dingo/models/versions/SQL/roc_dingo_0032__downgrade.sql
roc/dingo/models/versions/SQL/roc_dingo_0032__upgrade.sql
roc/dingo/models/versions/roc_dingo_0001_initial_.py
roc/dingo/models/versions/roc_dingo_0004_modify_file_log.py
roc/dingo/models/versions/roc_dingo_0005_rename_column_type_to_level.py
roc/dingo/models/versions/roc_dingo_0006_add_is_removed_.py
roc/dingo/models/versions/roc_dingo_0007_add_error_log_.py
roc/dingo/models/versions/roc_dingo_0008_remove_date_.py
roc/dingo/models/versions/roc_dingo_0009_add_bia_.py
roc/dingo/models/versions/roc_dingo_0010_add_view_.py
roc/dingo/models/versions/roc_dingo_0011_update_packet_.py
roc/dingo/models/versions/roc_dingo_0012_add_data_.py
roc/dingo/models/versions/roc_dingo_0013_fix_db_.py
roc/dingo/models/versions/roc_dingo_0014_add_solohk_.py
roc/dingo/models/versions/roc_dingo_0015_add_processqueue_.py
roc_dingo-1.6.2.dist-info/LICENSE
roc_dingo-1.6.2.dist-info/METADATA
roc_dingo-1.6.2.dist-info/WHEEL
roc_dingo-1.6.2.dist-info/RECORD
